MANIFEST.in
README.md
setup.py
bin/3diax
diax/__init__.py
diax/aioclient.py
diax/client.py
diax/errors.py
diax/log.py
diax/main.py
diax/model.py
diax/scripting.py
diax/services.py
diax/uri.py
diax/users.py
diax.egg-info/PKG-INFO
diax.egg-info/SOURCES.txt
diax.egg-info/dependency_links.txt
diax.egg-info/requires.txt
diax.egg-info/top_level.txt