Metadata-Version: 1.0
Name: diax
Version: 1.21
Summary: The official client to the 3DIAX API
Home-page: UNKNOWN
Author: Authentise, Inc.
Author-email: engineering@authentise.com
License: UNKNOWN
Platform: UNKNOWN
